src/__init__.py
src/consts.py
src/customlogger.py
src/extractonator.py
src/keycollator.py
src/proceduretimer.py
keycollator-0.0.6.dist-info/LICENSE
keycollator-0.0.6.dist-info/METADATA
keycollator-0.0.6.dist-info/WHEEL
keycollator-0.0.6.dist-info/entry_points.txt
keycollator-0.0.6.dist-info/top_level.txt
keycollator-0.0.6.dist-info/RECORD
