Metadata-Version: 2.1
Name: keycollator
Version: 0.0.6
Summary: Compares text in a file to reference/glossary/key-items/dictionary file.
Home-page: https://github.com/davidprush/keycollator
Author: David Rush
Author-email: davidprush@gmail.com
Project-URL: Homepage, https://github.com/davidprush/keycollator
Project-URL: Bug Tracker, https://github.com/davidprush/keycollator/issues
Classifier: Development Status :: 2 - Pre-Alpha
Classifier: Environment :: Console
Classifier: Intended Audience :: Developers
Classifier: Intended Audience :: Information Technology
Classifier: Intended Audience :: Education
Classifier: Intended Audience :: End Users/Desktop
Classifier: Intended Audience :: Science/Research
Classifier: Natural Language :: English
Classifier: Operating System :: MacOS :: MacOS X
Classifier: Operating System :: Microsoft :: Windows
Classifier: Operating System :: POSIX
Classifier: Topic :: Office/Business
Classifier: Topic :: Software Development :: Testing
Classifier: Topic :: Text Processing
Classifier: Topic :: Utilities
Classifier: Programming Language :: Python :: 3.7
Classifier: Programming Language :: Python :: 3.8
Classifier: Programming Language :: Python :: 3.9
Classifier: Programming Language :: Python :: 3.10
License-File: LICENSE
Requires-Dist: click (>=8.0.2)
Requires-Dist: datetime (>=4.7)
Requires-Dist: fuzzywuzzy (>=0.18.0)
Requires-Dist: halo (>=0.0.31)
Requires-Dist: nltk (>=3.7)
Requires-Dist: python-Levenshtein (>=0.12.2)
Requires-Dist: termtables (>=0.2.4)
Requires-Dist: numpy (>=1.23.3)
Requires-Dist: joblib (>=1.2.0)
Provides-Extra: pdf
Requires-Dist: ReportLab (>=1.2) ; extra == 'pdf'
Requires-Dist: RXP ; extra == 'pdf'
Provides-Extra: rest
Requires-Dist: docutils (>=0.3) ; extra == 'rest'
Requires-Dist: pack (==1.1,==1.3) ; extra == 'rest'
